plywood_gallery/__init__.py
plywood_gallery/browser_utils.py
plywood_gallery/generate_html.py
plywood_gallery/jinja2_template/template_index.html
plywood_gallery/plywood_tools.py
plywood_gallery/quickstart.py
plywood_gallery/quickstart_template/gallery_assets/Chapter_1_001_Foo.png
plywood_gallery/quickstart_template/gallery_assets/Chapter_2_002_Bar.png
plywood_gallery/quickstart_template/gallery_assets/Chapter_2_003_HelloWorld.png
plywood_gallery/quickstart_template/gallery_assets/gallery_parameters.json
plywood_gallery/quickstart_template/gallery_config.yaml
plywood_gallery/quickstart_template/gallery_notebook.ipynb
plywood_gallery/quickstart_template/html_build.ipynb
plywood_gallery/quickstart_template/icon.png
plywood_gallery/quickstart_template/preview_image.png
plywood_gallery-0.0.12.dist-info/METADATA
plywood_gallery-0.0.12.dist-info/LICENSE
plywood_gallery-0.0.12.dist-info/WHEEL
plywood_gallery-0.0.12.dist-info/RECORD
