Metadata-Version: 2.1
Name: plywood-gallery
Version: 0.0.12
Summary: Jupyter cell magic that turns images from cell output into a  gallery
Home-page: https://kolibril13.github.io/plywood-gallery/
License: MIT
Author: kolibril13
Requires-Python: >=3.8,<3.14
Classifier: License :: OSI Approved :: MIT License
Classifier: Programming Language :: Python :: 3
Classifier: Programming Language :: Python :: 3.8
Classifier: Programming Language :: Python :: 3.9
Classifier: Programming Language :: Python :: 3.10
Classifier: Programming Language :: Python :: 3.11
Requires-Dist: Flask (>=2.0.2)
Requires-Dist: Jinja2 (>=3.1.1)
Requires-Dist: Pillow (>=9.0.0,<10.0.0)
Requires-Dist: PyYAML (>=6.0)
Requires-Dist: ipykernel (>=6.7.0)
Requires-Dist: ipython (>=7.31.0)
Requires-Dist: watchdog (>=2.1.6)
Project-URL: Repository, https://github.com/kolibril13/plywood-gallery
